seledri/__init__.py
seledri/functionmap.py
seledri/timekeeper.py
seledri/worker.py
seledri/tests/__init__.py
seledri/tests/test_function_map.py
seledri/tests/test_module.py
seledri-0.1.3.dist-info/LICENSE
seledri-0.1.3.dist-info/METADATA
seledri-0.1.3.dist-info/WHEEL
seledri-0.1.3.dist-info/top_level.txt
seledri-0.1.3.dist-info/RECORD
